string_to_markdown_id/__init__.py
string_to_markdown_id/main.py
string_to_markdown_id-0.0.1.dist-info/METADATA
string_to_markdown_id-0.0.1.dist-info/WHEEL
string_to_markdown_id-0.0.1.dist-info/top_level.txt
string_to_markdown_id-0.0.1.dist-info/RECORD
