Metadata-Version: 2.1
Name: string-to-markdown-id
Version: 0.0.1
Summary: Convert string to GitLab Flavored Markdown Header ID
Home-page: https://github.com/PROxZIMA/string_to_markdown_id
Author: PROxZIMA
Author-email: contact@proxzima.dev
Maintainer: PROxZIMA
Maintainer-email: contact@proxzima.dev
License: MIT license
Keywords: string_to_markdown_id
Platform: UNKNOWN
Classifier: Development Status :: 3 - Alpha
Classifier: Intended Audience :: Developers
Classifier: Programming Language :: Python :: 3.6
Classifier: Programming Language :: Python :: 3.7
Classifier: Programming Language :: Python :: 3.8
